__init__.py
dq_suite/__init__.py
dq_suite/common.py
dq_suite/other.py
dq_suite/output_transformations.py
dq_suite/validation.py
dq_suite/validation_input.py
dq_suite/custom_renderers/__init__.py
dq_suite/custom_renderers/slack_renderer.py
dq_suite/profile/generic_rules.py
dq_suite/profile/profile.py
dq_suite/profile/rules_module.py
dq_suite/schemas/__init__.py
dq_suite/schemas/afwijking.py
dq_suite/schemas/bronattribuut.py
dq_suite/schemas/brondataset.py
dq_suite/schemas/brontabel.py
dq_suite/schemas/regel.py
dq_suite/schemas/regel_id_input.py
dq_suite/schemas/validatie.py
dq_suite_amsterdam-0.13.0.dist-info/licenses/LICENSE
dq_suite_amsterdam-0.13.0.dist-info/METADATA
dq_suite_amsterdam-0.13.0.dist-info/WHEEL
dq_suite_amsterdam-0.13.0.dist-info/top_level.txt
dq_suite_amsterdam-0.13.0.dist-info/RECORD
