Metadata-Version: 2.4
Name: dq-suite-amsterdam
Version: 0.13.0
Summary: Wrapper for Great Expectations to fit the requirements of the Gemeente Amsterdam.
Author-email: Arthur Kordes <a.kordes@amsterdam.nl>, Aysegul Cayir Aydar <a.cayiraydar@amsterdam.nl>, Rajesh Chellaswamy <r.chellaswamy@amsterdam.nl>, Bas Schotten <b.schotten@amsterdam.nl>
Requires-Python: >=3.10
License-File: LICENSE
Requires-Dist: great_expectations==1.1.3
Requires-Dist: pandas==2.1.4
Requires-Dist: pyspark==3.5.2
Requires-Dist: pyhumps==3.8.0
Requires-Dist: pyyaml==6.0.3
Requires-Dist: delta-spark~=3.2.0
Requires-Dist: validators==0.34.0
Requires-Dist: typing_extensions>=4.7.1
Requires-Dist: ydata-profiling==4.18.0
Provides-Extra: dev
Requires-Dist: bandit~=1.7; extra == "dev"
Requires-Dist: black~=23.1; extra == "dev"
Requires-Dist: pytest~=7.2; extra == "dev"
Requires-Dist: mypy~=1.4.1; extra == "dev"
Requires-Dist: pylint~=2.16; extra == "dev"
Requires-Dist: autoflake~=2.0.1; extra == "dev"
Requires-Dist: coverage~=7.6.1; extra == "dev"
Requires-Dist: chispa~=0.10.1; extra == "dev"
Dynamic: license-file
